qmtools/__init__.py
qmtools/_core.py
qmtools/graph/__init__.py
qmtools/graph/_graph.py
qmtools-0.1b0.dist-info/LICENSE
qmtools-0.1b0.dist-info/METADATA
qmtools-0.1b0.dist-info/WHEEL
qmtools-0.1b0.dist-info/top_level.txt
qmtools-0.1b0.dist-info/RECORD
