Metadata-Version: 2.1
Name: qmtools
Version: 0.1b0
Summary: Quantum Mechanic Tools for Python.
Home-page: UNKNOWN
Author: Samuel Huff Dieterich
Author-email: samuel.dieterich@ufrgs.br
License: UNKNOWN
Project-URL: Source, https://github.com/SamuelHDieterich/qmtools
Project-URL: Bug Tracker, https://github.com/SamuelHDieterich/qmtools/issues
Platform: UNKNOWN
Classifier: Programming Language :: Python
Classifier: Programming Language :: Python :: 3
Classifier: Programming Language :: Python :: 3.6
Classifier: Programming Language :: Python :: 3.7
Classifier: Programming Language :: Python :: 3.8
Classifier: Programming Language :: Python :: 3.9
Classifier: Programming Language :: Python :: 3.10
Classifier: License :: OSI Approved :: GNU General Public License v3 (GPLv3)
Classifier: Operating System :: OS Independent
Requires-Python: >=3.6.5
License-File: LICENSE
Requires-Dist: numpy
Requires-Dist: scipy
Requires-Dist: attrs
